keras_textclassification/__init__.py
keras_textclassification/text_classification_api.py
keras_textclassification/base/__init__.py
keras_textclassification/base/embedding.py
keras_textclassification/base/graph.py
keras_textclassification/conf/__init__.py
keras_textclassification/conf/logger_config.py
keras_textclassification/conf/path_config.py
keras_textclassification/data/__init__.py
keras_textclassification/data/model/__init__.py
keras_textclassification/data/model/fast_text/__init__.py
keras_textclassification/data_preprocess/__init__.py
keras_textclassification/data_preprocess/data_split.py
keras_textclassification/data_preprocess/generator_preprocess.py
keras_textclassification/data_preprocess/text_preprocess.py
keras_textclassification/keras_layers/__init__.py
keras_textclassification/keras_layers/attention_dot.py
keras_textclassification/keras_layers/attention_self.py
keras_textclassification/keras_layers/capsule.py
keras_textclassification/keras_layers/highway.py
keras_textclassification/keras_layers/k_max_pooling.py
keras_textclassification/keras_layers/keras_lookahead.py
keras_textclassification/keras_layers/keras_radam.py
keras_textclassification/keras_layers/non_mask_layer.py
keras_textclassification/keras_layers/transformer.py
keras_textclassification/keras_layers/albert/__init__.py
keras_textclassification/keras_layers/albert/albert.py
keras_textclassification/keras_layers/transformer_utils/__init__.py
keras_textclassification/keras_layers/transformer_utils/embedding.py
keras_textclassification/keras_layers/transformer_utils/feedforward.py
keras_textclassification/keras_layers/transformer_utils/layer_normalization.py
keras_textclassification/keras_layers/transformer_utils/multi_head_attention.py
keras_textclassification/keras_layers/transformer_utils/scale_dot_product_attention.py
keras_textclassification/keras_layers/transformer_utils/triangle_position_embedding.py
keras_textclassification/m00_Albert/__init__.py
Keras_TextClassification-0.1.7.dist-info/LICENSE
Keras_TextClassification-0.1.7.dist-info/METADATA
Keras_TextClassification-0.1.7.dist-info/WHEEL
Keras_TextClassification-0.1.7.dist-info/top_level.txt
Keras_TextClassification-0.1.7.dist-info/RECORD
